[
    {
      "id": 1,
      "name": "Tanvir Hasan Soyon",
      "img": "",
      "designation": "",
      "mobile": "",
      "bloodGroup": "",
      "facebook": "",
      "address": "Jorargonj,Mirsarai, Chittagong Cantonment",
      "education": "International Islamic University Chittagong"
    },
    {
      "id": 2,
      "name": "Akhi Rahman",
      "img": "",
      "designation": "",
      "mobile": "",
      "bloodGroup": "",
      "facebook": "",
      "address": "Buet,Dhaka",
      "education": "International Islamic University Chittagong"
    },
    {
      "id": 3,
      "name": "Shahin kawsar",
      "img": "",
      "designation": "",
      "mobile": "",
      "bloodGroup": "",
      "facebook": "",
      "address": "Nazir road, Feni",
      "education": "JB high school"
    },
    {
      "id": 4,
      "name": "Alif Hasan Saikat",
      "img": "",
      "designation": "",
      "mobile": "",
      "bloodGroup": "",
      "facebook": "",
      "address": "Zorarganj, Mirsari, Chittagong",
      "education": "IIUC"
    },
    {
      "id": 5,
      "name": "Md. Arafat uddin sakib",
      "img": "",
      "designation": "",
      "mobile": "",
      "bloodGroup": "",
      "facebook": "",
      "address": "Tejgao, Dhaka",
      "education": "Government city college"
    },
    {
      "id": 6,
      "name": "Abu Nidal Patwary",
      "img": "",
      "designation": "",
      "mobile": "",
      "bloodGroup": "",
      "facebook": "",
      "address": "Chottogram",
      "education": "ChatChattogram Cantonment public college"
    },
    {
      "id": 7,
      "name": "Mohammad Refat Uddin",
      "img": "",
      "designation": "",
      "mobile": "",
      "bloodGroup": "",
      "facebook": "",
      "address": "Jalalpur Central Eidgah, Pabna Sadar, Pabna",
      "education": "Bangladesh University of Engineering & Technology"
    },
    {
      "id": 8,
      "name": "Md.Manjur Hossain Mahi",
      "img": "",
      "designation": "",
      "mobile": "",
      "bloodGroup": "",
      "facebook": "",
      "address": "Chittagong Town",
      "education": "Feni government college"
    },
    {
      "id": 9,
      "name": "Faria Ali",
      "img": "",
      "designation": "",
      "mobile": "",
      "bloodGroup": "",
      "facebook": "",
      "address": "Cumilla",
      "education": "University Of Dhaka"
    },
    {
      "id": 10,
      "name": "Nazmul Hossain Emon",
      "img": "",
      "designation": "",
      "mobile": "",
      "bloodGroup": "",
      "facebook": "",
      "address": "Muraripur Mirsari chittagong",
      "education": "Institution of health technology"
    },
    {
      "id": 11,
      "name": "Muntasir Bin Mujib",
      "img": "",
      "designation": "",
      "mobile": "",
      "bloodGroup": "",
      "facebook": "",
      "address": "Chittagong",
      "education": "Pabna University of Science and Technology"
    },
    {
      "id": 12,
      "name": "Abdur Rakib",
      "img": "",
      "designation": "",
      "mobile": "",
      "bloodGroup": "",
      "facebook": "",
      "address": "A.K khan,Ctg",
      "education": "Government Commerce College of Chittagong"
    },
    {
      "id": 13,
      "name": "Anis Uddin",
      "img": "",
      "designation": "",
      "mobile": "",
      "bloodGroup": "",
      "facebook": "",
      "address": "East bhagabotipur,Zorargan, mirsarai,Chattogram",
      "education": "Mirsarai DegreeCollege"
    }
]